mergefast/.clang-format
mergefast/.gitignore
mergefast/__init__.py
mergefast/bind.c
mergefast/merge.c
mergefast/merge.h
mergefast-1.1.2.dist-info/METADATA
mergefast-1.1.2.dist-info/WHEEL
mergefast-1.1.2.dist-info/RECORD
