Metadata-Version: 2.1
Name: mergefast
Version: 1.1.2
Summary: 
Author: Adam Gordon Bell
Author-email: adam@corecursive.com
Requires-Python: >=3.11,<4.0
Classifier: Programming Language :: Python :: 3
Classifier: Programming Language :: Python :: 3.11
Requires-Dist: matplotlib (>=3.8.0,<4.0.0)
